mltype/__init__.py
mltype/base.py
mltype/cli.py
mltype/data.py
mltype/interactive.py
mltype/ml.py
mltype/stats.py
mltype/utils.py
mltype-0.3.dist-info/LICENSE
mltype-0.3.dist-info/METADATA
mltype-0.3.dist-info/WHEEL
mltype-0.3.dist-info/entry_points.txt
mltype-0.3.dist-info/top_level.txt
mltype-0.3.dist-info/RECORD
